{"stats":{"minecraft:used":{"minecraft:moss_block":2,"minecraft:beetroot":4,"minecraft:writable_book":3,"minecraft:ladder":37,"minecraft:spruce_slab":12,"minecraft:poppy":2,"minecraft:chest":41,"minecraft:quartz_stairs":20,"minecraft:stone":24,"minecraft:soul_sand":16,"minecraft:cocoa_beans":3,"minecraft:snowball":4,"minecraft:acacia_sapling":1,"minecraft:azure_bluet":3,"minecraft:stripped_spruce_log":89,"minecraft:lava_bucket":7,"minecraft:red_wool":19,"minecraft:grass_block":3,"minecraft:birch_sapling":12,"minecraft:quartz_block":122,"minecraft:cherry_leaves":1,"minecraft:dark_oak_slab":11,"minecraft:stone_brick_stairs":1,"minecraft:bow":148,"minecraft:sweet_berries":10,"minecraft:furnace":11,"minecraft:oak_sapling":128,"minecraft:cooked_cod":1,"minecraft:egg":33,"minecraft:potato":504,"minecraft:seagrass":51,"minecraft:short_grass":5,"minecraft:diorite":18,"minecraft:mossy_stone_bricks":31,"minecraft:stripped_birch_log":7,"minecraft:blackstone":36,"minecraft:wooden_pickaxe":13,"minecraft:mossy_stone_brick_stairs":18,"minecraft:composter":1,"minecraft:oak_leaves":87,"minecraft:glow_berries":2,"minecraft:golden_apple":3,"minecraft:sand":151,"minecraft:blast_furnace":4,"minecraft:birch_fence":56,"minecraft:crying_obsidian":9,"minecraft:chiseled_sandstone":1,"minecraft:birch_slab":3,"minecraft:stone_button":5,"minecraft:white_glazed_terracotta":3,"minecraft:lectern":2,"minecraft:oak_pressure_plate":17,"minecraft:nether_wart_block":4,"minecraft:diamond_sword":2408,"minecraft:fire_charge":1,"minecraft:smithing_table":4,"minecraft:dark_oak_fence":57,"minecraft:bubble_coral_block":5,"minecraft:birch_log":7,"minecraft:oak_boat":2,"minecraft:oak_trapdoor":50,"minecraft:acacia_log":8,"minecraft:dead_tube_coral_block":3,"minecraft:stone_sword":280,"minecraft:enchanting_table":3,"minecraft:armor_stand":26,"minecraft:cooked_salmon":16,"minecraft:netherrack":3831,"minecraft:torch":515,"minecraft:orange_bed":4,"minecraft:anvil":1,"minecraft:brewing_stand":5,"minecraft:target":3,"minecraft:ancient_debris":1,"minecraft:warped_wart_block":13,"minecraft:nether_quartz_ore":1,"minecraft:twisting_vines":10,"minecraft:cod_bucket":3,"minecraft:nether_brick_stairs":9,"minecraft:oak_fence_gate":21,"minecraft:fern":3,"minecraft:shroomlight":77,"minecraft:chipped_anvil":2,"minecraft:iron_axe":1610,"minecraft:totem_of_undying":1,"minecraft:barrel":21,"minecraft:smooth_basalt":6,"minecraft:diamond_chestplate":1,"minecraft:basalt":46,"minecraft:glowstone":21,"minecraft:goat_horn":24,"minecraft:pointed_dripstone":8,"minecraft:cobbled_deepslate":302,"minecraft:horn_coral_fan":3,"minecraft:calcite":11,"minecraft:wheat_seeds":1540,"minecraft:water_bucket":475,"minecraft:chiseled_bookshelf":1,"minecraft:warped_stem":8,"minecraft:tube_coral_block":5,"minecraft:birch_planks":748,"minecraft:cartography_table":2,"minecraft:bubble_coral_fan":3,"minecraft:cauldron":3,"minecraft:polished_blackstone_bricks":8,"minecraft:gilded_blackstone":17,"minecraft:salmon":1,"minecraft:diamond_block":6,"minecraft:mossy_cobblestone":31,"minecraft:vine":2,"minecraft:rail":3,"minecraft:red_bed":1,"minecraft:tnt":42,"minecraft:crafting_table":36,"minecraft:oak_slab":16,"minecraft:fire_coral":2,"minecraft:white_bed":152,"minecraft:campfire":41,"minecraft:dark_oak_fence_gate":1,"minecraft:spruce_log":1,"minecraft:oak_log":72,"minecraft:mud":1,"minecraft:oxeye_daisy":3,"minecraft:diamond_pickaxe":1774,"minecraft:cornflower":13,"minecraft:diamond_shovel":329,"minecraft:sunflower":14,"minecraft:oak_button":2,"minecraft:iron_pickaxe":4339,"minecraft:spruce_trapdoor":91,"minecraft:spruce_sapling":7,"minecraft:chiseled_stone_bricks":21,"minecraft:cobblestone":985,"minecraft:cooked_porkchop":115,"minecraft:glass_pane":118,"minecraft:dandelion":55,"minecraft:kelp":221,"minecraft:stripped_oak_log":20,"minecraft:jukebox":3,"minecraft:diamond_leggings":3,"minecraft:iron_shovel":1680,"minecraft:bone_block":5,"minecraft:iron_sword":1589,"minecraft:nether_wart":6,"minecraft:bell":4,"minecraft:sculk_sensor":3,"minecraft:iron_chestplate":2,"minecraft:nether_bricks":20,"minecraft:carrot":309,"minecraft:tuff":15,"minecraft:music_disc_13":3,"minecraft:beehive":8,"minecraft:obsidian":17,"minecraft:milk_bucket":1,"minecraft:big_dripleaf":1,"minecraft:glass":171,"minecraft:lantern":38,"minecraft:iron_helmet":2,"minecraft:stone_bricks":63,"minecraft:golden_sword":79,"minecraft:item_frame":20,"minecraft:birch_trapdoor":15,"minecraft:repeater":13,"minecraft:red_carpet":5,"minecraft:redstone_lamp":2,"minecraft:honeycomb_block":2,"minecraft:magma_block":2,"minecraft:scaffolding":1,"minecraft:warped_fungus":1,"minecraft:hay_block":10,"minecraft:mangrove_roots":2,"minecraft:beetroot_seeds":34,"minecraft:polished_diorite_stairs":1,"minecraft:golden_boots":3,"minecraft:dark_oak_stairs":33,"minecraft:tube_coral_fan":2,"minecraft:stone_pickaxe":2253,"minecraft:oak_planks":652,"minecraft:polished_diorite_slab":3,"minecraft:sandstone":43,"minecraft:sugar_cane":6,"minecraft:white_wool":6,"minecraft:crossbow":4,"minecraft:dripstone_block":11,"minecraft:shears":381,"minecraft:redstone_torch":34,"minecraft:sticky_piston":56,"minecraft:lever":20,"minecraft:melon_slice":128,"minecraft:heavy_weighted_pressure_plate":4,"minecraft:bread":970,"minecraft:dark_oak_log":1,"minecraft:string":3,"minecraft:iron_door":1,"minecraft:gravel":63,"minecraft:stripped_oak_wood":3,"minecraft:grindstone":3,"minecraft:cooked_rabbit":1,"minecraft:andesite":136,"minecraft:chain":3,"minecraft:bone_meal":58,"minecraft:chest_minecart":1,"minecraft:air":1,"minecraft:tropical_fish_bucket":1,"minecraft:golden_pickaxe":32,"minecraft:experience_bottle":7,"minecraft:oak_fence":134,"minecraft:rose_bush":25,"minecraft:flint_and_steel":97,"minecraft:music_disc_otherside":3,"minecraft:tropical_fish":1,"minecraft:stone_shovel":2516,"minecraft:redstone":116,"minecraft:spruce_planks":17,"minecraft:ender_chest":5,"minecraft:stone_hoe":140,"minecraft:stripped_birch_wood":2,"minecraft:cooked_chicken":38,"minecraft:dirt":2053,"minecraft:spyglass":14,"minecraft:white_carpet":1,"minecraft:spruce_stairs":166,"minecraft:cobblestone_wall":13,"minecraft:golden_chestplate":4,"minecraft:spruce_fence":1,"minecraft:bee_nest":3,"minecraft:salmon_bucket":2,"minecraft:granite":12,"minecraft:birch_door":15,"minecraft:brown_terracotta":127,"minecraft:dark_oak_planks":335,"minecraft:bookshelf":27,"minecraft:red_tulip":16,"minecraft:oak_stairs":32,"minecraft:polished_blackstone_brick_stairs":1,"minecraft:iron_boots":2,"minecraft:crimson_planks":102,"minecraft:light_gray_wool":1,"minecraft:black_stained_glass":5,"minecraft:soul_soil":1,"minecraft:netherite_pickaxe":490,"minecraft:horn_coral_block":1,"minecraft:cooked_beef":26,"minecraft:light_gray_bed":1,"minecraft:mossy_stone_brick_wall":12,"minecraft:pumpkin":3,"minecraft:iron_leggings":3,"minecraft:cooked_mutton":22,"minecraft:polished_andesite":5,"minecraft:baked_potato":519,"minecraft:blue_wool":14,"minecraft:stonecutter":1,"minecraft:cobblestone_slab":9,"minecraft:warped_roots":12,"minecraft:glow_item_frame":36,"minecraft:music_disc_cat":2,"minecraft:terracotta":2,"minecraft:red_mushroom":1,"minecraft:painting":22,"minecraft:smoker":4,"minecraft:warped_planks":53,"minecraft:flower_pot":1,"minecraft:black_wool":2,"minecraft:wooden_hoe":57,"minecraft:apple":2,"minecraft:cracked_polished_blackstone_bricks":10,"minecraft:map":5,"minecraft:golden_leggings":3,"minecraft:stone_axe":1825,"minecraft:pink_petals":63,"minecraft:fishing_rod":7,"minecraft:white_banner":11,"minecraft:bucket":510,"minecraft:sea_pickle":60,"minecraft:smooth_stone":8,"minecraft:birch_stairs":31},"minecraft:broken":{"minecraft:golden_boots":2,"minecraft:iron_boots":1,"minecraft:iron_chestplate":1,"minecraft:iron_leggings":1,"minecraft:golden_sword":2,"minecraft:iron_sword":7,"minecraft:crossbow":1,"minecraft:stone_sword":2,"minecraft:stone_hoe":1,"minecraft:iron_axe":6,"minecraft:iron_pickaxe":15,"minecraft:iron_helmet":1,"minecraft:golden_helmet":1,"minecraft:iron_shovel":6,"minecraft:golden_leggings":3,"minecraft:stone_pickaxe":17,"minecraft:stone_axe":13,"minecraft:stone_shovel":18,"minecraft:golden_chestplate":3,"minecraft:flint_and_steel":1,"minecraft:golden_pickaxe":1},"minecraft:killed_by":{"minecraft:piglin_brute":10,"minecraft:pillager":1,"minecraft:ravager":2,"minecraft:magma_cube":2,"minecraft:vindicator":14,"minecraft:zombie":13,"minecraft:vex":2,"minecraft:warden":9,"minecraft:zombified_piglin":1,"minecraft:wither_skeleton":1,"minecraft:creeper":8,"minecraft:drowned":2,"minecraft:piglin":3,"minecraft:cave_spider":2,"minecraft:blaze":6,"minecraft:player":3,"minecraft:spider":2,"minecraft:enderman":12,"minecraft:bee":1,"minecraft:hoglin":2,"minecraft:skeleton":14},"minecraft:killed":{"minecraft:cave_spider":3,"minecraft:skeleton":214,"minecraft:guardian":1,"minecraft:chicken":32,"minecraft:tropical_fish":1,"minecraft:magma_cube":57,"minecraft:salmon":11,"minecraft:pillager":116,"minecraft:goat":1,"minecraft:zombie":251,"minecraft:glow_squid":1,"minecraft:cow":30,"minecraft:evoker":5,"minecraft:vindicator":23,"minecraft:husk":2,"minecraft:wandering_trader":4,"minecraft:ravager":3,"minecraft:enderman":28,"minecraft:zombified_piglin":5,"minecraft:witch":5,"minecraft:spider":82,"minecraft:bee":2,"minecraft:silverfish":4,"minecraft:turtle":3,"minecraft:piglin_brute":9,"minecraft:piglin":40,"minecraft:pig":41,"minecraft:zombie_villager":4,"minecraft:strider":1,"minecraft:creeper":70,"minecraft:sheep":54,"minecraft:trader_llama":7,"minecraft:ghast":13,"minecraft:blaze":16,"minecraft:vex":6,"minecraft:slime":1,"minecraft:phantom":2,"minecraft:drowned":16,"minecraft:bat":1,"minecraft:hoglin":12,"minecraft:squid":6,"minecraft:wither_skeleton":10},"minecraft:mined":{"minecraft:dark_oak_planks":110,"minecraft:stripped_warped_stem":2,"minecraft:white_bed":10,"minecraft:fire_coral_wall_fan":2,"minecraft:jungle_leaves":10,"minecraft:obsidian":5,"minecraft:granite":122,"minecraft:chiseled_polished_blackstone":2,"minecraft:acacia_log":52,"minecraft:horn_coral_fan":1,"minecraft:oak_pressure_plate":1,"minecraft:bubble_coral_block":6,"minecraft:tube_coral_block":11,"minecraft:oxeye_daisy":3,"minecraft:nether_wart":6,"minecraft:chiseled_stone_bricks":5,"minecraft:spawner":1,"minecraft:weeping_vines_plant":6,"minecraft:polished_blackstone_bricks":20,"minecraft:tall_seagrass":40,"minecraft:magma_block":14,"minecraft:sticky_piston":53,"minecraft:cobbled_deepslate":69,"minecraft:barrel":3,"minecraft:fire":1332,"minecraft:moss_carpet":1,"minecraft:pumpkin":3,"minecraft:deepslate_lapis_ore":32,"minecraft:nether_brick_stairs":33,"minecraft:enchanting_table":2,"minecraft:twisting_vines":2,"minecraft:sculk_shrieker":6,"minecraft:dirt_path":86,"minecraft:small_amethyst_bud":1,"minecraft:oak_stairs":16,"minecraft:white_banner":2,"minecraft:orange_bed":8,"minecraft:piston_head":3,"minecraft:cut_sandstone":4,"minecraft:red_bed":3,"minecraft:kelp_plant":43,"minecraft:crimson_nylium":17,"minecraft:smoker":1,"minecraft:soul_fire":38,"minecraft:amethyst_cluster":12,"minecraft:powder_snow":20,"minecraft:torch":221,"minecraft:blast_furnace":1,"minecraft:melon":22,"minecraft:dead_bush":8,"minecraft:polished_diorite_slab":3,"minecraft:glass":20,"minecraft:smooth_quartz_slab":1,"minecraft:tube_coral_fan":3,"minecraft:sugar_cane":21,"minecraft:amethyst_block":12,"minecraft:birch_sapling":2,"minecraft:polished_diorite_stairs":1,"minecraft:chain":12,"minecraft:repeater":9,"minecraft:mud":1,"minecraft:wheat":789,"minecraft:jukebox":1,"minecraft:birch_door":8,"minecraft:warped_fungus":2,"minecraft:stone_brick_stairs":1,"minecraft:oak_fence_gate":3,"minecraft:smooth_basalt":9,"minecraft:red_mushroom_block":3,"minecraft:deepslate":358,"minecraft:mossy_cobblestone":13,"minecraft:stripped_birch_log":13,"minecraft:dark_oak_log":124,"minecraft:sea_lantern":2,"minecraft:nether_bricks":124,"minecraft:dark_oak_fence":15,"minecraft:spruce_fence":1,"minecraft:crimson_roots":2,"minecraft:redstone_wire":88,"minecraft:kelp":26,"minecraft:cartography_table":2,"minecraft:moss_block":2,"minecraft:horn_coral_wall_fan":6,"minecraft:horn_coral":2,"minecraft:redstone_ore":4,"minecraft:andesite":283,"minecraft:diamond_block":6,"minecraft:white_glazed_terracotta":3,"minecraft:potatoes":5,"minecraft:vine":186,"minecraft:cobblestone_slab":5,"minecraft:rail":70,"minecraft:warped_stem":156,"minecraft:brain_coral_wall_fan":4,"minecraft:bamboo":6,"minecraft:bone_block":69,"minecraft:white_wool":76,"minecraft:fire_coral_block":1,"minecraft:brain_coral":1,"minecraft:ender_chest":4,"minecraft:smithing_table":3,"minecraft:birch_stairs":30,"minecraft:oak_slab":1,"minecraft:redstone_block":4,"minecraft:glass_pane":8,"minecraft:soul_sand":5,"minecraft:dandelion":52,"minecraft:fire_coral":4,"minecraft:cornflower":24,"minecraft:short_grass":1219,"minecraft:emerald_ore":2,"minecraft:warped_roots":24,"minecraft:campfire":4,"minecraft:copper_ore":5,"minecraft:tall_grass":154,"minecraft:deepslate_gold_ore":41,"minecraft:diorite":231,"minecraft:big_dripleaf":1,"minecraft:warped_wart_block":50,"minecraft:black_stained_glass":5,"minecraft:cobblestone_wall":2,"minecraft:white_carpet":1,"minecraft:spruce_log":183,"minecraft:birch_leaves":29,"minecraft:mangrove_leaves":1,"minecraft:sunflower":8,"minecraft:gravel":325,"minecraft:dripstone_block":13,"minecraft:cobweb":26,"minecraft:brown_terracotta":135,"minecraft:stone_bricks":14,"minecraft:gold_ore":3,"minecraft:chipped_anvil":2,"minecraft:deepslate_emerald_ore":1,"minecraft:fern":29,"minecraft:large_amethyst_bud":2,"minecraft:spruce_planks":4,"minecraft:stone_pressure_plate":1,"minecraft:oak_sapling":7,"minecraft:sculk_vein":5,"minecraft:potted_cactus":1,"minecraft:brewing_stand":5,"minecraft:spruce_trapdoor":20,"minecraft:budding_amethyst":1,"minecraft:grass_block":1594,"minecraft:dead_tube_coral_block":1,"minecraft:cracked_polished_blackstone_bricks":11,"minecraft:bubble_coral_fan":4,"minecraft:soul_soil":1,"minecraft:composter":1,"minecraft:gilded_blackstone":1,"minecraft:smooth_stone":2,"minecraft:glowstone":85,"minecraft:iron_ore":101,"minecraft:target":2,"minecraft:anvil":1,"minecraft:azure_bluet":3,"minecraft:pointed_dripstone":4,"minecraft:red_tulip":69,"minecraft:spruce_slab":2,"minecraft:deepslate_redstone_ore":18,"minecraft:quartz_block":12,"minecraft:blackstone":207,"minecraft:twisting_vines_plant":14,"minecraft:medium_amethyst_bud":5,"minecraft:orange_terracotta":1,"minecraft:clay":25,"minecraft:calcite":16,"minecraft:poppy":3,"minecraft:chest":12,"minecraft:nether_quartz_ore":275,"minecraft:cobblestone":328,"minecraft:honeycomb_block":2,"minecraft:grindstone":2,"minecraft:prismarine":4,"minecraft:oak_planks":186,"minecraft:iron_door":3,"minecraft:wall_torch":200,"minecraft:cauldron":2,"minecraft:pink_petals":43,"minecraft:seagrass":31,"minecraft:warped_nylium":17,"minecraft:dark_oak_slab":7,"minecraft:mossy_stone_brick_wall":2,"minecraft:nether_wart_block":6,"minecraft:warped_planks":4,"minecraft:birch_log":288,"minecraft:birch_trapdoor":8,"minecraft:stripped_oak_wood":2,"minecraft:brown_wall_banner":2,"minecraft:tnt":8,"minecraft:oak_log":1409,"minecraft:beetroots":3,"minecraft:sand":813,"minecraft:dirt":2056,"minecraft:tripwire_hook":4,"minecraft:netherrack":2667,"minecraft:ancient_debris":42,"minecraft:oak_leaves":409,"minecraft:horn_coral_block":1,"minecraft:redstone_lamp":2,"minecraft:nether_gold_ore":61,"minecraft:crying_obsidian":4,"minecraft:tuff":14,"minecraft:quartz_stairs":2,"minecraft:deepslate_diamond_ore":378,"minecraft:candle":1,"minecraft:red_stained_glass":6,"minecraft:mangrove_roots":2,"minecraft:glow_lichen":5,"minecraft:lever":23,"minecraft:chiseled_bookshelf":1,"minecraft:tube_coral_wall_fan":3,"minecraft:stone_button":4,"minecraft:weeping_vines":1,"minecraft:spruce_leaves":34,"minecraft:sandstone":66,"minecraft:crimson_stem":34,"minecraft:mangrove_propagule":2,"minecraft:large_fern":9,"minecraft:hay_block":159,"minecraft:oak_trapdoor":9,"minecraft:furnace":3,"minecraft:nether_sprouts":2,"minecraft:polished_basalt":2,"minecraft:chiseled_sandstone":2,"minecraft:stripped_spruce_log":108,"minecraft:gold_block":23,"minecraft:bell":3,"minecraft:nether_brick_fence":51,"minecraft:bookshelf":48,"minecraft:shroomlight":82,"minecraft:deepslate_iron_ore":86,"minecraft:lantern":15,"minecraft:stripped_oak_log":30,"minecraft:stone":1630,"minecraft:podzol":8,"minecraft:acacia_leaves":32,"minecraft:scaffolding":1,"minecraft:red_wool":3,"minecraft:snow_block":1,"minecraft:basalt":65,"minecraft:oak_fence":46,"minecraft:crafting_table":16,"minecraft:rose_bush":6,"minecraft:sculk_sensor":15,"minecraft:lectern":1,"minecraft:lapis_ore":20,"minecraft:polished_blackstone_brick_stairs":1,"minecraft:sculk":495,"minecraft:spruce_stairs":23,"minecraft:birch_planks":79,"minecraft:bubble_coral":1,"minecraft:sea_pickle":28,"minecraft:beehive":6,"minecraft:redstone_torch":31,"minecraft:sweet_berry_bush":1,"minecraft:white_wall_banner":12,"minecraft:bee_nest":5,"minecraft:yellow_bed":2,"minecraft:coal_ore":544,"minecraft:cocoa":1,"minecraft:cherry_leaves":4,"minecraft:bubble_coral_wall_fan":5,"minecraft:cracked_stone_bricks":2,"minecraft:terracotta":2,"minecraft:polished_andesite":5,"minecraft:mossy_stone_bricks":14,"minecraft:birch_fence":1},"minecraft:crafted":{"minecraft:ender_chest":2,"minecraft:smooth_stone":20,"minecraft:dark_oak_pressure_plate":1,"minecraft:oak_pressure_plate":16,"minecraft:blaze_powder":13,"minecraft:chain":2,"minecraft:birch_slab":36,"minecraft:bookshelf":28,"minecraft:cooked_mutton":68,"minecraft:glass":308,"minecraft:quartz_block":154,"minecraft:diamond_helmet":1,"minecraft:repeater":4,"minecraft:diamond_leggings":1,"minecraft:netherite_boots":1,"minecraft:birch_door":12,"minecraft:cooked_rabbit":1,"minecraft:target":1,"minecraft:cooked_porkchop":50,"minecraft:glow_item_frame":6,"minecraft:smithing_table":1,"minecraft:mossy_cobblestone":34,"minecraft:copper_ingot":3,"minecraft:hay_block":3,"minecraft:campfire":41,"minecraft:painting":2,"minecraft:light_gray_bed":1,"minecraft:lectern":1,"minecraft:wooden_hoe":2,"minecraft:golden_leggings":1,"minecraft:compass":2,"minecraft:iron_pickaxe":16,"minecraft:iron_block":59,"minecraft:gold_ingot":184,"minecraft:netherite_ingot":11,"minecraft:birch_stairs":20,"minecraft:golden_carrot":37,"minecraft:stone_shovel":19,"minecraft:smooth_stone_slab":6,"minecraft:jukebox":2,"minecraft:iron_nugget":279,"minecraft:spyglass":1,"minecraft:bone_meal":597,"minecraft:white_carpet":18,"minecraft:lantern":31,"minecraft:diamond":9,"minecraft:dark_oak_fence":54,"minecraft:spruce_stairs":168,"minecraft:stripped_birch_wood":3,"minecraft:ladder":93,"minecraft:spruce_slab":138,"minecraft:stone_pickaxe":17,"minecraft:diamond_boots":1,"minecraft:dark_oak_planks":556,"minecraft:wheat":1440,"minecraft:coal_block":7,"minecraft:crossbow":3,"minecraft:netherite_pickaxe":1,"minecraft:enchanting_table":1,"minecraft:red_carpet":18,"minecraft:glowstone":28,"minecraft:oak_fence_gate":18,"minecraft:mossy_stone_brick_stairs":20,"minecraft:oak_stairs":16,"minecraft:birch_trapdoor":10,"minecraft:writable_book":1,"minecraft:iron_shovel":8,"minecraft:iron_leggings":1,"minecraft:armor_stand":3,"minecraft:white_bed":141,"minecraft:oak_planks":2180,"minecraft:cobblestone_slab":6,"minecraft:barrel":18,"minecraft:cooked_chicken":24,"minecraft:stone":192,"minecraft:heavy_weighted_pressure_plate":2,"minecraft:warped_planks":476,"minecraft:stone_brick_slab":36,"minecraft:bow":8,"minecraft:iron_boots":2,"minecraft:chest":29,"minecraft:netherite_helmet":1,"minecraft:oak_button":1,"minecraft:netherite_upgrade_smithing_template":30,"minecraft:chiseled_stone_bricks":16,"minecraft:stone_hoe":3,"minecraft:ender_eye":13,"minecraft:stone_bricks":140,"minecraft:oak_fence":93,"minecraft:golden_sword":1,"minecraft:smoker":3,"minecraft:honeycomb_block":2,"minecraft:quartz_stairs":28,"minecraft:oak_slab":42,"minecraft:item_frame":15,"minecraft:arrow":48,"minecraft:cauldron":1,"minecraft:crafting_table":25,"minecraft:map":3,"minecraft:spruce_planks":752,"minecraft:iron_helmet":2,"minecraft:baked_potato":839,"minecraft:wooden_pickaxe":1,"minecraft:red_wool":17,"minecraft:gold_block":17,"minecraft:birch_planks":1044,"minecraft:tnt":32,"minecraft:spruce_trapdoor":80,"minecraft:dark_oak_slab":12,"minecraft:book":9,"minecraft:iron_chestplate":2,"minecraft:paper":33,"minecraft:diamond_pickaxe":2,"minecraft:birch_fence":57,"minecraft:stick":808,"minecraft:iron_ingot":289,"minecraft:stone_sword":2,"minecraft:redstone_torch":11,"minecraft:dark_oak_fence_gate":1,"minecraft:shears":4,"minecraft:oak_door":3,"minecraft:redstone":36,"minecraft:coal":36,"minecraft:beehive":2,"minecraft:golden_chestplate":1,"minecraft:mossy_stone_bricks":66,"minecraft:stone_button":2,"minecraft:furnace":13,"minecraft:blast_furnace":3,"minecraft:mossy_stone_brick_wall":12,"minecraft:oak_trapdoor":54,"minecraft:diamond_block":58,"minecraft:glass_pane":176,"minecraft:netherite_chestplate":1,"minecraft:netherite_leggings":1,"minecraft:iron_axe":8,"minecraft:cobblestone_wall":18,"minecraft:chiseled_bookshelf":1,"minecraft:netherite_scrap":43,"minecraft:cooked_beef":27,"minecraft:red_dye":43,"minecraft:cooked_cod":1,"minecraft:crimson_planks":112,"minecraft:diamond_sword":2,"minecraft:dark_oak_stairs":40,"minecraft:iron_sword":4,"minecraft:cooked_salmon":5,"minecraft:stripped_oak_wood":3,"minecraft:bucket":6,"minecraft:stone_axe":14,"minecraft:mossy_cobblestone_wall":12,"minecraft:air":0,"minecraft:bread":947,"minecraft:blue_dye":14,"minecraft:oak_boat":2,"minecraft:white_wool":9,"minecraft:gold_nugget":297,"minecraft:blue_wool":14,"minecraft:stonecutter":1,"minecraft:acacia_planks":20,"minecraft:torch":96,"minecraft:diamond_chestplate":1},"minecraft:custom":{"minecraft:interact_with_crafting_table":609,"minecraft:open_barrel":299,"minecraft:bell_ring":101,"minecraft:leave_game":46,"minecraft:time_since_death":6947,"minecraft:play_time":4070086,"minecraft:deaths":284,"minecraft:jump":76205,"minecraft:enchant_item":60,"minecraft:interact_with_furnace":323,"minecraft:play_record":8,"minecraft:interact_with_cartography_table":21,"minecraft:sleep_in_bed":91,"minecraft:damage_dealt":225156,"minecraft:interact_with_smoker":146,"minecraft:use_cauldron":2,"minecraft:inspect_dispenser":5,"minecraft:horse_one_cm":323433,"minecraft:interact_with_smithing_table":21,"minecraft:interact_with_anvil":40,"minecraft:inspect_hopper":2,"minecraft:sneak_time":167299,"minecraft:interact_with_lectern":15,"minecraft:interact_with_blast_furnace":142,"minecraft:total_world_time":4070086,"minecraft:interact_with_stonecutter":7,"minecraft:time_since_rest":6294,"minecraft:swim_one_cm":1658799,"minecraft:fly_one_cm":19031654,"minecraft:open_chest":3349,"minecraft:fish_caught":1,"minecraft:fall_one_cm":2217021,"minecraft:animals_bred":8,"minecraft:sprint_one_cm":13131439,"minecraft:drop":801,"minecraft:talked_to_villager":19,"minecraft:interact_with_brewingstand":6,"minecraft:walk_on_water_one_cm":745939,"minecraft:open_enderchest":310,"minecraft:player_kills":29,"minecraft:crouch_one_cm":658496,"minecraft:mob_kills":1262,"minecraft:fill_cauldron":5,"minecraft:interact_with_campfire":20,"minecraft:climb_one_cm":259134,"minecraft:walk_one_cm":8934317,"minecraft:raid_win":3,"minecraft:walk_under_water_one_cm":498599,"minecraft:boat_one_cm":523213,"minecraft:raid_trigger":2,"minecraft:pot_flower":1,"minecraft:interact_with_grindstone":37,"minecraft:damage_taken":125214,"minecraft:damage_absorbed":120},"minecraft:dropped":{"minecraft:iron_sword":2,"minecraft:lapis_lazuli":302,"minecraft:glow_ink_sac":4,"minecraft:glass_bottle":2,"minecraft:diamond":129,"minecraft:crafting_table":1,"minecraft:crossbow":5,"minecraft:weeping_vines":3,"minecraft:warped_roots":12,"minecraft:saddle":1,"minecraft:brown_banner":2,"minecraft:rail":7,"minecraft:dirt":761,"minecraft:chain":8,"minecraft:gold_nugget":132,"minecraft:bone_meal":128,"minecraft:sunflower":13,"minecraft:sand":267,"minecraft:iron_pickaxe":3,"minecraft:white_wool":25,"minecraft:birch_stairs":1,"minecraft:bone":13,"minecraft:sugar_cane":1,"minecraft:iron_nugget":15,"minecraft:cobbled_deepslate":21,"minecraft:wheat":3,"minecraft:obsidian":11,"minecraft:rotten_flesh":196,"minecraft:oak_planks":328,"minecraft:enchanted_golden_apple":1,"minecraft:nether_brick_fence":50,"minecraft:salmon":1,"minecraft:charcoal":2,"minecraft:glass":120,"minecraft:warped_wart_block":33,"minecraft:iron_ingot":98,"minecraft:enchanted_book":7,"minecraft:golden_boots":3,"minecraft:birch_leaves":1,"minecraft:wheat_seeds":222,"minecraft:golden_horse_armor":1,"minecraft:book":50,"minecraft:feather":29,"minecraft:cobblestone":488,"minecraft:prismarine_crystals":6,"minecraft:granite":36,"minecraft:coal":7,"minecraft:golden_apple":1,"minecraft:acacia_sign":1,"minecraft:lava_bucket":28,"minecraft:ink_sac":20,"minecraft:wooden_hoe":1,"minecraft:stripped_birch_log":1,"minecraft:oak_stairs":1,"minecraft:white_banner":7,"minecraft:iron_shovel":1,"minecraft:string":43,"minecraft:polished_diorite_slab":4,"minecraft:stone_sword":3,"minecraft:cobblestone_wall":6,"minecraft:white_carpet":4,"minecraft:clay_ball":8,"minecraft:name_tag":1,"minecraft:nether_bricks":122,"minecraft:shears":2,"minecraft:pumpkin_seeds":16,"minecraft:diamond_sword":3,"minecraft:potato":192,"minecraft:shroomlight":42,"minecraft:stone":2,"minecraft:sea_pickle":2,"minecraft:diamond_pickaxe":1,"minecraft:spider_eye":16,"minecraft:bamboo":47,"minecraft:sandstone":13,"minecraft:bow":5,"minecraft:magma_block":4,"minecraft:nether_brick_stairs":25,"minecraft:warped_stem":26,"minecraft:soul_sand":2,"minecraft:warped_fungus":1,"minecraft:oak_log":231,"minecraft:leather":24,"minecraft:iron_horse_armor":2,"minecraft:cod":1,"minecraft:flint":4,"minecraft:cracked_polished_blackstone_bricks":1,"minecraft:polished_diorite_stairs":8,"minecraft:crimson_roots":1,"minecraft:seagrass":1,"minecraft:gilded_blackstone":7,"minecraft:amethyst_shard":8,"minecraft:gold_ingot":15,"minecraft:gravel":222,"minecraft:blackstone":46,"minecraft:spyglass":2,"minecraft:twisting_vines":9,"minecraft:cherry_sapling":2,"minecraft:beetroot":1,"minecraft:gunpowder":19,"minecraft:birch_trapdoor":1,"minecraft:glowstone":2,"minecraft:beetroot_seeds":4,"minecraft:melon_seeds":3,"minecraft:basalt":17,"minecraft:arrow":34,"minecraft:quartz":25,"minecraft:oak_leaves":29,"minecraft:netherrack":51,"minecraft:water_bucket":3,"minecraft:stone_hoe":1,"minecraft:bread":172,"minecraft:oak_slab":5,"minecraft:diamond_leggings":1,"minecraft:poisonous_potato":2,"minecraft:golden_axe":1,"minecraft:amethyst_block":4,"minecraft:copper_ingot":2,"minecraft:acacia_log":4,"minecraft:stick":44,"minecraft:iron_block":3,"minecraft:diorite":151,"minecraft:torch":70,"minecraft:nether_wart_block":2,"minecraft:melon_slice":8,"minecraft:iron_door":1,"minecraft:iron_axe":2,"minecraft:cactus":1,"minecraft:pink_petals":3,"minecraft:bucket":8,"minecraft:redstone_block":5,"minecraft:redstone":7,"minecraft:polished_diorite":112,"minecraft:warped_nylium":2,"minecraft:coarse_dirt":29,"minecraft:nether_wart":4,"minecraft:blaze_rod":2,"minecraft:raw_copper":2,"minecraft:tuff":2,"minecraft:totem_of_undying":1,"minecraft:flint_and_steel":1,"minecraft:filled_map":15,"minecraft:andesite":70,"minecraft:mossy_stone_bricks":1,"minecraft:golden_leggings":1,"minecraft:oak_sapling":2,"minecraft:golden_sword":5,"minecraft:stone_pickaxe":1,"minecraft:wooden_pickaxe":1,"minecraft:raw_gold":38,"minecraft:nautilus_shell":1},"minecraft:picked_up":{"minecraft:seagrass":52,"minecraft:birch_door":18,"minecraft:iron_chestplate":2,"minecraft:flower_pot":1,"minecraft:anvil":1,"minecraft:prismarine_shard":2,"minecraft:smithing_table":3,"minecraft:lead":22,"minecraft:diamond_sword":3,"minecraft:oak_stairs":17,"minecraft:enchanted_book":8,"minecraft:golden_shovel":1,"minecraft:brewing_stand":5,"minecraft:golden_sword":8,"minecraft:amethyst_block":10,"minecraft:polished_blackstone_brick_stairs":1,"minecraft:music_disc_cat":2,"minecraft:string":124,"minecraft:dark_oak_pressure_plate":1,"minecraft:soul_soil":1,"minecraft:cooked_salmon":5,"minecraft:shroomlight":86,"minecraft:beetroot":30,"minecraft:diamond_leggings":4,"minecraft:gold_nugget":355,"minecraft:cobbled_deepslate":459,"minecraft:spruce_planks":10,"minecraft:horn_coral_block":1,"minecraft:acacia_sign":2,"minecraft:bubble_coral":1,"minecraft:enchanted_golden_apple":1,"minecraft:melon_slice":136,"minecraft:coal_block":4,"minecraft:golden_helmet":2,"minecraft:white_glazed_terracotta":3,"minecraft:beehive":6,"minecraft:jukebox":1,"minecraft:composter":1,"minecraft:big_dripleaf":1,"minecraft:acacia_log":52,"minecraft:golden_axe":1,"minecraft:honeycomb_block":2,"minecraft:warped_planks":4,"minecraft:golden_chestplate":3,"minecraft:cauldron":2,"minecraft:orange_bed":7,"minecraft:stone_sword":4,"minecraft:horn_coral_fan":3,"minecraft:tropical_fish":1,"minecraft:red_tulip":67,"minecraft:iron_block":58,"minecraft:netherite_chestplate":1,"minecraft:blaze_rod":11,"minecraft:snowball":4,"minecraft:birch_log":284,"minecraft:magma_block":13,"minecraft:polished_diorite_slab":11,"minecraft:feather":39,"minecraft:cooked_beef":80,"minecraft:iron_door":4,"minecraft:cherry_leaves":1,"minecraft:birch_slab":19,"minecraft:water_bucket":5,"minecraft:smoker":1,"minecraft:flint":67,"minecraft:netherite_leggings":2,"minecraft:map":1,"minecraft:lantern":15,"minecraft:disc_fragment_5":1,"minecraft:twisting_vines":19,"minecraft:chipped_anvil":2,"minecraft:rabbit":1,"minecraft:diamond_helmet":1,"minecraft:glowstone_dust":228,"minecraft:moss_block":2,"minecraft:honeycomb":90,"minecraft:warped_wart_block":47,"minecraft:stripped_spruce_log":105,"minecraft:ink_sac":23,"minecraft:dark_oak_log":164,"minecraft:barrel":3,"minecraft:polished_andesite":5,"minecraft:lever":25,"minecraft:granite":123,"minecraft:golden_horse_armor":1,"minecraft:bread":293,"minecraft:dark_oak_fence":19,"minecraft:crimson_roots":1,"minecraft:diamond_pickaxe":3,"minecraft:mud":1,"minecraft:crafting_table":16,"minecraft:bee_nest":3,"minecraft:bubble_coral_fan":3,"minecraft:nether_wart":11,"minecraft:clay_ball":93,"minecraft:golden_pickaxe":1,"minecraft:redstone_lamp":2,"minecraft:fire_coral":2,"minecraft:heavy_weighted_pressure_plate":2,"minecraft:cornflower":27,"minecraft:red_bed":3,"minecraft:flint_and_steel":4,"minecraft:white_carpet":5,"minecraft:iron_shovel":3,"minecraft:cracked_stone_bricks":1,"minecraft:cartography_table":2,"minecraft:stripped_warped_stem":2,"minecraft:music_disc_otherside":3,"minecraft:beef":37,"minecraft:iron_nugget":21,"minecraft:poppy":3,"minecraft:spruce_slab":128,"minecraft:quartz_stairs":12,"minecraft:chest":12,"minecraft:birch_sapling":13,"minecraft:egg":33,"minecraft:black_stained_glass":5,"minecraft:sandstone":59,"minecraft:stone":17,"minecraft:oak_door":3,"minecraft:glow_item_frame":27,"minecraft:spruce_fence":1,"minecraft:carrot":676,"minecraft:redstone":236,"minecraft:netherite_pickaxe":1,"minecraft:prismarine_crystals":6,"minecraft:tnt":7,"minecraft:diamond_chestplate":1,"minecraft:beetroot_seeds":91,"minecraft:tube_coral_fan":3,"minecraft:shears":2,"minecraft:diamond_boots":1,"minecraft:hay_block":168,"minecraft:tube_coral_block":9,"minecraft:gold_ingot":2,"minecraft:totem_of_undying":6,"minecraft:glow_berries":47,"minecraft:mutton":69,"minecraft:white_wool":556,"minecraft:bone_block":68,"minecraft:rail":74,"minecraft:oxeye_daisy":3,"minecraft:stripped_oak_log":30,"minecraft:birch_leaves":1,"minecraft:tripwire_hook":4,"minecraft:fern":3,"minecraft:red_mushroom":1,"minecraft:filled_map":51,"minecraft:oak_log":1448,"minecraft:ancient_debris":42,"minecraft:golden_boots":5,"minecraft:paper":20,"minecraft:white_banner":20,"minecraft:apple":17,"minecraft:stone_bricks":12,"minecraft:kelp":221,"minecraft:warped_stem":151,"minecraft:oak_fence_gate":3,"minecraft:stone_pickaxe":2,"minecraft:glass_bottle":2,"minecraft:iron_sword":5,"minecraft:dark_oak_stairs":7,"minecraft:smooth_basalt":8,"minecraft:milk_bucket":1,"minecraft:dark_oak_slab":19,"minecraft:sweet_berries":10,"minecraft:red_wool":3,"minecraft:spyglass":3,"minecraft:gravel":328,"minecraft:birch_stairs":31,"minecraft:spruce_sapling":7,"minecraft:spruce_log":181,"minecraft:crying_obsidian":4,"minecraft:diamond_shovel":1,"minecraft:slime_ball":1,"minecraft:polished_diorite":168,"minecraft:stone_axe":1,"minecraft:short_grass":5,"minecraft:painting":20,"minecraft:warped_roots":26,"minecraft:oak_button":1,"minecraft:brown_banner":2,"minecraft:melon_seeds":3,"minecraft:warped_nylium":2,"minecraft:ender_pearl":12,"minecraft:wheat":1267,"minecraft:nether_brick_fence":50,"minecraft:redstone_block":9,"minecraft:ender_chest":3,"minecraft:potion":2,"minecraft:gilded_blackstone":1,"minecraft:stone_brick_stairs":1,"minecraft:dead_tube_coral_block":3,"minecraft:raw_copper":23,"minecraft:iron_leggings":6,"minecraft:armor_stand":23,"minecraft:sticky_piston":56,"minecraft:sea_pickle":62,"minecraft:activator_rail":1,"minecraft:smooth_stone":2,"minecraft:bucket":18,"minecraft:eye_armor_trim_smithing_template":1,"minecraft:rose_bush":25,"minecraft:redstone_torch":32,"minecraft:cobblestone_slab":7,"minecraft:calcite":13,"minecraft:iron_pickaxe":2,"minecraft:iron_boots":2,"minecraft:furnace":4,"minecraft:stick":205,"minecraft:birch_trapdoor":13,"minecraft:brown_terracotta":143,"minecraft:oak_fence":53,"minecraft:torch":602,"minecraft:spruce_stairs":48,"minecraft:porkchop":53,"minecraft:target":2,"minecraft:pointed_dripstone":8,"minecraft:diorite":237,"minecraft:vine":193,"minecraft:goat_horn":1,"minecraft:quartz_block":15,"minecraft:cactus":2,"minecraft:rotten_flesh":228,"minecraft:mangrove_roots":2,"minecraft:fire_coral_fan":1,"minecraft:obsidian":29,"minecraft:cod":2,"minecraft:blaze_powder":1,"minecraft:cobblestone":3047,"minecraft:nautilus_shell":2,"minecraft:enchanting_table":2,"minecraft:pink_petals":138,"minecraft:magma_cream":18,"minecraft:repeater":9,"minecraft:andesite":363,"minecraft:golden_leggings":1,"minecraft:potato":1639,"minecraft:tuff":20,"minecraft:lapis_lazuli":739,"minecraft:dirt":4606,"minecraft:stripped_birch_log":13,"minecraft:name_tag":4,"minecraft:glass":87,"minecraft:bone":206,"minecraft:bow":18,"minecraft:wheat_seeds":3974,"minecraft:raw_gold":69,"minecraft:bell":4,"minecraft:grindstone":3,"minecraft:mossy_stone_bricks":15,"minecraft:bamboo":47,"minecraft:prismarine":4,"minecraft:oak_planks":391,"minecraft:mossy_stone_brick_stairs":2,"minecraft:brain_coral":1,"minecraft:cooked_porkchop":88,"minecraft:music_disc_13":3,"minecraft:oak_pressure_plate":1,"minecraft:poisonous_potato":14,"minecraft:sand":876,"minecraft:nether_brick_stairs":34,"minecraft:grass_block":5,"minecraft:diamond_block":6,"minecraft:chiseled_sandstone":1,"minecraft:mossy_cobblestone":19,"minecraft:sugar":2,"minecraft:diamond":794,"minecraft:netherite_helmet":2,"minecraft:cracked_polished_blackstone_bricks":11,"minecraft:crossbow":15,"minecraft:emerald":20,"minecraft:oak_sapling":130,"minecraft:netherrack":4800,"minecraft:bubble_coral_block":6,"minecraft:oak_leaves":128,"minecraft:cocoa_beans":3,"minecraft:charcoal":8,"minecraft:azure_bluet":3,"minecraft:chicken":30,"minecraft:ladder":2,"minecraft:chest_minecart":1,"minecraft:wooden_pickaxe":1,"minecraft:gold_block":23,"minecraft:chain":12,"minecraft:shield":1,"minecraft:oak_trapdoor":21,"minecraft:iron_axe":4,"minecraft:item_frame":11,"minecraft:birch_fence":5,"minecraft:blackstone":195,"minecraft:detector_rail":3,"minecraft:mossy_cobblestone_wall":12,"minecraft:echo_shard":4,"minecraft:light_gray_wool":5,"minecraft:lectern":1,"minecraft:sugar_cane":40,"minecraft:spruce_trapdoor":28,"minecraft:phantom_membrane":2,"minecraft:raw_iron":263,"minecraft:copper_ingot":4,"minecraft:polished_blackstone_bricks":15,"minecraft:stone_button":4,"minecraft:iron_horse_armor":2,"minecraft:stone_pressure_plate":1,"minecraft:dark_oak_planks":192,"minecraft:arrow":255,"minecraft:weeping_vines":3,"minecraft:golden_hoe":1,"minecraft:nether_bricks":148,"minecraft:saddle":6,"minecraft:ward_armor_trim_smithing_template":1,"minecraft:netherite_boots":2,"minecraft:basalt":63,"minecraft:glow_ink_sac":33,"minecraft:crimson_stem":28,"minecraft:salmon":12,"minecraft:cut_sandstone":1,"minecraft:leather":54,"minecraft:birch_planks":81,"minecraft:cobblestone_wall":1,"minecraft:nether_wart_block":6,"minecraft:gunpowder":102,"minecraft:wooden_hoe":1,"minecraft:orange_terracotta":1,"minecraft:cooked_mutton":15,"minecraft:red_carpet":5,"minecraft:fire_coral_block":1,"minecraft:heart_of_the_sea":1,"minecraft:iron_ingot":81,"minecraft:cooked_chicken":23,"minecraft:stripped_oak_wood":2,"minecraft:mossy_stone_brick_wall":4,"minecraft:acacia_sapling":1,"minecraft:soul_sand":18,"minecraft:book":276,"minecraft:scaffolding":1,"minecraft:oak_slab":3,"minecraft:warped_fungus":3,"minecraft:nether_quartz_ore":1,"minecraft:pumpkin":4,"minecraft:chiseled_stone_bricks":5,"minecraft:stone_brick_slab":4,"minecraft:quartz":651,"minecraft:dandelion":58,"minecraft:dripstone_block":11,"minecraft:lava_bucket":5,"minecraft:brain_coral_fan":1,"minecraft:amethyst_shard":79,"minecraft:blast_furnace":1,"minecraft:white_bed":11,"minecraft:spider_eye":19,"minecraft:polished_diorite_stairs":13,"minecraft:pumpkin_seeds":16,"minecraft:iron_helmet":2,"minecraft:cherry_sapling":3,"minecraft:terracotta":2,"minecraft:black_wool":2,"minecraft:coal":852,"minecraft:sunflower":27}},"DataVersion":3700}